[
 {
  "id": "ml-doc-classification-2026-06-25",
  "title": "ML Models — document classification training",
  "feature": "ML Models — document classification training",
  "date": "2026-06-25",
  "participant": "Andrei",
  "file": "sessions/ml-doc-classification-2026-06-25.html",
  "topics": [
   "AI assistance",
   "Auto-label & manual review",
   "Candidate vs promote",
   "Classifier setup & copy",
   "Confusion matrix & comparison",
   "Data lifecycle & re-labeling",
   "Navigation & discoverability",
   "Train / test split"
  ],
  "insights": 20,
  "published": "2026-06-26"
 }
]